LICENSE
MANIFEST.in
README.md
easyquery.py
setup.py
easyquery.egg-info/PKG-INFO
easyquery.egg-info/SOURCES.txt
easyquery.egg-info/dependency_links.txt
easyquery.egg-info/requires.txt
easyquery.egg-info/top_level.txt