Metadata-Version: 2.1
Name: easyquery
Version: 0.3.0
Summary: Create easy-to-use Query objects that can apply on NumPy structured arrays, astropy Table, and Pandas DataFrame.
Home-page: https://github.com/yymao/easyquery
Author: Yao-Yuan Mao
Author-email: yymao.astro@gmail.com
Maintainer: Yao-Yuan Mao
Maintainer-email: yymao.astro@gmail.com
License: MIT
Download-URL: https://github.com/yymao/easyquery/archive/v0.3.0.tar.gz
Keywords: easyquery query numpy
Platform: UNKNOWN
Classifier: Intended Audience :: Developers
Classifier: Intended Audience :: Science/Research
Classifier: License :: OSI Approved :: MIT License
Classifier: Programming Language :: Python :: 3.6
Classifier: Programming Language :: Python :: 3.7
Classifier: Programming Language :: Python :: 3.8
Classifier: Programming Language :: Python :: 3.9
Requires-Python: >=3.6
License-File: LICENSE
